optimpv/__init__.py
optimpv/BayesInfEmcee/EmceeOptimizer.py
optimpv/BayesInfEmcee/__init__.py
optimpv/DDfits/CVAgent.py
optimpv/DDfits/HysteresisAgent.py
optimpv/DDfits/IMPSAgent.py
optimpv/DDfits/ImpedanceAgent.py
optimpv/DDfits/JVAgent.py
optimpv/DDfits/SIMsalabimAgent.py
optimpv/DDfits/__init__.py
optimpv/DDfits/old/CVAgent.py
optimpv/DDfits/old/HysteresisAgent.py
optimpv/DDfits/old/IMPSAgent.py
optimpv/DDfits/old/ImpedanceAgent.py
optimpv/DDfits/old/JVAgent.py
optimpv/DDfits/old/SIMsalabimAgent.py
optimpv/DDfits/old/__init__.py
optimpv/Diodefits/DiodeAgent.py
optimpv/Diodefits/DiodeModel.py
optimpv/Diodefits/__init__.py
optimpv/RateEqfits/Pumps.py
optimpv/RateEqfits/RateEqAgent.py
optimpv/RateEqfits/RateEqModel.py
optimpv/RateEqfits/__init__.py
optimpv/TransferMatrix/TransferMatrixAgent.py
optimpv/TransferMatrix/TransferMatrixModel.py
optimpv/TransferMatrix/__init__.py
optimpv/axBOtorch/EGBO.py
optimpv/axBOtorch/TURBO.py
optimpv/axBOtorch/__init__.py
optimpv/axBOtorch/axBOtorchOptimizer.py
optimpv/axBOtorch/axSchedulerUtils.py
optimpv/axBOtorch/axUtils.py
optimpv/general/BaseAgent.py
optimpv/general/FitParams.py
optimpv/general/SuggestOnlyAgent.py
optimpv/general/__init__.py
optimpv/general/general.py
optimpv/general/logger.py
optimpv/posterior/__init__.py
optimpv/posterior/posterior.py
optimpv/pymooOpti/__init__.py
optimpv/pymooOpti/pymooOptimizer.py
optimpv/scipyOpti/__init__.py
optimpv/scipyOpti/scipyOptimizer.py
optimpv/tests/__init__.py
optimpv/tests/test_axBOtorch.py
optimpv/tests/test_emcee.py
optimpv/tests/test_pymoo.py
optimpv/tests/test_scipy.py
optimpv-1.4.dist-info/licenses/LICENSE
optimpv-1.4.dist-info/METADATA
optimpv-1.4.dist-info/WHEEL
optimpv-1.4.dist-info/top_level.txt
optimpv-1.4.dist-info/RECORD
