Metadata-Version: 2.4
Name: optimpv
Version: 1.4
Summary: optimPV: Optimization & Modeling tools for PV research
Home-page: https://github.com/openPV-lab/optimPV
Download-URL: https://github.com/openPV-lab/optimPV/v1.04.tar.gz
Author: Vincent M. Le Corre
Author-email: 
License: GPLv3
Keywords: Bayesian optimization,Evolutionary optimization,parameter extraction,experimental design,high throughput,solar cells
Classifier: Programming Language :: Python :: 3
Classifier: Intended Audience :: Science/Research
Classifier: Operating System :: OS Independent
Classifier: License :: OSI Approved :: GNU General Public License v3 (GPLv3)
Requires-Python: >=3.12
License-File: LICENSE
Requires-Dist: numpy<=2.0,>=1.2
Requires-Dist: pandas>=1.4
Requires-Dist: matplotlib>=3.5
Requires-Dist: jupyterlab>=3.4
Requires-Dist: seaborn>=0.11
Requires-Dist: scipy>=1.0
Requires-Dist: gitpython>=3.1
Requires-Dist: openpyxl>=3.0
Requires-Dist: pyodbc>=4.0
Requires-Dist: scikit-optimize>=0.9
Requires-Dist: pySIMsalabim>=1.3
Requires-Dist: tk
Requires-Dist: torch>=2.0
Requires-Dist: torchvision>=0.15
Requires-Dist: torchaudio>=2.0
Requires-Dist: emcee>=3.1
Requires-Dist: pymoo>=0.6
Requires-Dist: ax-platform>=1.1.0
Provides-Extra: dev
Requires-Dist: pytest; extra == "dev"
Requires-Dist: twine; extra == "dev"
Dynamic: author
Dynamic: classifier
Dynamic: description
Dynamic: description-content-type
Dynamic: download-url
Dynamic: home-page
Dynamic: keywords
Dynamic: license
Dynamic: license-file
Dynamic: provides-extra
Dynamic: requires-dist
Dynamic: requires-python
Dynamic: summary
